{
  "spx": {
    "price": 6637.03,
    "chgAbs": -79.0598,
    "chgPct": -1.1772,
    "ma50": 6873.07,
    "ma200": 6615.76
  },
  "ndx": {
    "price": 24498.44,
    "chgAbs": -281.9799,
    "chgPct": -1.1379,
    "ma50": 25168.53,
    "ma200": 24334.03
  },
  "ibex": {
    "price": 17299.1,
    "chgAbs": 50.4008,
    "chgPct": 0.2922,
    "ma50": 17725.73,
    "ma200": 15960.87
  },
  "btc": {
    "price": 71174.99,
    "chgAbs": -2747.4866,
    "chgPct": -3.7167,
    "ma50": 70504.66,
    "ma200": 93390.34
  },
  "vix": {
    "price": 24.08,
    "chgAbs": 1.71,
    "chgPct": 7.6442,
    "ma50": 19.51,
    "ma200": 17.63
  },
  "gold": {
    "price": 4851.0,
    "chgAbs": -150.0,
    "chgPct": -2.9994,
    "ma50": 4946.24,
    "ma200": 4050.76
  },
  "oil": {
    "price": 97.08,
    "chgAbs": 0.87,
    "chgPct": 0.9043,
    "ma50": 69.09,
    "ma200": 64.32
  },
  "eurusd": {
    "price": 1.1482,
    "chgAbs": -0.0018,
    "chgPct": -0.1525,
    "ma50": 1.17,
    "ma200": 1.17
  },
  "dxy": {
    "price": 100.495,
    "chgAbs": 0.755,
    "chgPct": 0.757,
    "ma50": 98.12,
    "ma200": 98.39
  },
  "ust10": {
    "price": 4.259,
    "chgAbs": 0.057,
    "chgPct": 1.3565,
    "ma50": 4.16,
    "ma200": 4.19
  },
  "ust2": {
    "price": 3.61,
    "chgAbs": 0.005,
    "chgPct": 0.1387,
    "ma50": 3.58,
    "ma200": 3.85
  },
  "_meta": {
    "updated_utc": "2026-03-18T19:37:09.215450+00:00",
    "ok": 11,
    "total": 11,
    "source": "Yahoo Finance (free, no API key)"
  }
}