{
  "spx": {
    "price": 6590.71,
    "chgAbs": 34.3399,
    "chgPct": 0.5238,
    "ma50": 6835.03,
    "ma200": 6630.82
  },
  "ndx": {
    "price": 24151.9,
    "chgAbs": 149.4508,
    "chgPct": 0.6226,
    "ma50": 25011.9,
    "ma200": 24395.72
  },
  "ibex": {
    "price": 17161.9,
    "chgAbs": 251.7008,
    "chgPct": 1.4885,
    "ma50": 17650.13,
    "ma200": 16030.74
  },
  "btc": {
    "price": 70857.44,
    "chgAbs": 339.5806,
    "chgPct": 0.4816,
    "ma50": 68935.87,
    "ma200": 91977.05
  },
  "vix": {
    "price": 25.67,
    "chgAbs": -1.28,
    "chgPct": -4.7495,
    "ma50": 20.62,
    "ma200": 17.84
  },
  "gold": {
    "price": 4555.0,
    "chgAbs": 155.7002,
    "chgPct": 3.5392,
    "ma50": 4948.09,
    "ma200": 4079.96
  },
  "oil": {
    "price": 89.76,
    "chgAbs": -2.59,
    "chgPct": -2.8045,
    "ma50": 72.58,
    "ma200": 65.04
  },
  "eurusd": {
    "price": 1.1569,
    "chgAbs": -0.0038,
    "chgPct": -0.3284,
    "ma50": 1.17,
    "ma200": 1.17
  },
  "dxy": {
    "price": 99.567,
    "chgAbs": 0.137,
    "chgPct": 0.1378,
    "ma50": 98.26,
    "ma200": 98.41
  },
  "ust10": {
    "price": 4.316,
    "chgAbs": -0.076,
    "chgPct": -1.7304,
    "ma50": 4.18,
    "ma200": 4.19
  },
  "ust2": {
    "price": 3.618,
    "chgAbs": -0.002,
    "chgPct": -0.0552,
    "ma50": 3.59,
    "ma200": 3.83
  },
  "_meta": {
    "updated_utc": "2026-03-25T15:53:12.074361+00:00",
    "ok": 11,
    "total": 11,
    "source": "Yahoo Finance (free, no API key)"
  }
}