{
  "spx": {
    "price": 7493.92,
    "chgAbs": 48.1998,
    "chgPct": 0.6473,
    "ma50": 6988.37,
    "ma200": 6807.76
  },
  "ndx": {
    "price": 29609.486,
    "chgAbs": 252.2165,
    "chgPct": 0.8591,
    "ma50": 26392.76,
    "ma200": 25258.97
  },
  "ibex": {
    "price": 18031.1,
    "chgAbs": 55.9008,
    "chgPct": 0.311,
    "ma50": 17632.11,
    "ma200": 16751.63
  },
  "btc": {
    "price": 76632.06,
    "chgAbs": -907.1119,
    "chgPct": -1.1699,
    "ma50": 76405.73,
    "ma200": 80790.64
  },
  "vix": {
    "price": 16.56,
    "chgAbs": -0.2,
    "chgPct": -1.1933,
    "ma50": 20.77,
    "ma200": 18.36
  },
  "gold": {
    "price": 4520.4,
    "chgAbs": -19.3998,
    "chgPct": -0.4273,
    "ma50": 4668.85,
    "ma200": 4348.52
  },
  "oil": {
    "price": 97.16,
    "chgAbs": 0.81,
    "chgPct": 0.8407,
    "ma50": 98.39,
    "ma200": 71.52
  },
  "eurusd": {
    "price": 1.1605,
    "chgAbs": -0.002,
    "chgPct": -0.175,
    "ma50": 1.17,
    "ma200": 1.17
  },
  "dxy": {
    "price": 99.328,
    "chgAbs": 0.138,
    "chgPct": 0.1391,
    "ma50": 98.97,
    "ma200": 98.55
  },
  "ust10": {
    "price": 4.578,
    "chgAbs": -0.008,
    "chgPct": -0.1744,
    "ma50": 4.37,
    "ma200": 4.2
  },
  "ust2": {
    "price": 3.588,
    "chgAbs": 0.006,
    "chgPct": 0.1675,
    "ma50": 3.6,
    "ma200": 3.71
  },
  "_meta": {
    "updated_utc": "2026-05-22T15:46:05.285954+00:00",
    "ok": 11,
    "total": 11,
    "source": "Yahoo Finance (free, no API key)"
  }
}