{
  "spx": {
    "price": 6967.38,
    "chgAbs": 81.1398,
    "chgPct": 1.1783,
    "ma50": 6760.88,
    "ma200": 6670.72
  },
  "ndx": {
    "price": 25841.996,
    "chgAbs": 458.2753,
    "chgPct": 1.8054,
    "ma50": 24679.44,
    "ma200": 24552.38
  },
  "ibex": {
    "price": 18184.9,
    "chgAbs": -101.1996,
    "chgPct": -0.5534,
    "ma50": 17640.85,
    "ma200": 16272.11
  },
  "btc": {
    "price": 74310.63,
    "chgAbs": 129.0206,
    "chgPct": 0.1739,
    "ma50": 69674.99,
    "ma200": 87344.9
  },
  "vix": {
    "price": 17.81,
    "chgAbs": -0.55,
    "chgPct": -2.9956,
    "ma50": 22.52,
    "ma200": 18.19
  },
  "gold": {
    "price": 4834.0,
    "chgAbs": 9.0,
    "chgPct": 0.1865,
    "ma50": 4897.63,
    "ma200": 4172.81
  },
  "oil": {
    "price": 92.08,
    "chgAbs": 0.8,
    "chgPct": 0.8764,
    "ma50": 83.48,
    "ma200": 67.25
  },
  "eurusd": {
    "price": 1.179,
    "chgAbs": 0.0021,
    "chgPct": 0.1796,
    "ma50": 1.17,
    "ma200": 1.17
  },
  "dxy": {
    "price": 98.18,
    "chgAbs": 0.06,
    "chgPct": 0.0611,
    "ma50": 98.66,
    "ma200": 98.49
  },
  "ust10": {
    "price": 4.264,
    "chgAbs": 0.008,
    "chgPct": 0.188,
    "ma50": 4.21,
    "ma200": 4.19
  },
  "ust2": {
    "price": 3.612,
    "chgAbs": 0.0,
    "chgPct": 0.0,
    "ma50": 3.6,
    "ma200": 3.79
  },
  "_meta": {
    "updated_utc": "2026-04-15T13:13:59.492061+00:00",
    "ok": 11,
    "total": 11,
    "source": "Yahoo Finance (free, no API key)"
  }
}