{
  "spx": {
    "price": 7477.22,
    "chgAbs": 31.4998,
    "chgPct": 0.4231,
    "ma50": 6988.03,
    "ma200": 6807.68
  },
  "ndx": {
    "price": 29494.553,
    "chgAbs": 137.2835,
    "chgPct": 0.4676,
    "ma50": 26390.46,
    "ma200": 25258.4
  },
  "ibex": {
    "price": 17985.3,
    "chgAbs": 10.1008,
    "chgPct": 0.0562,
    "ma50": 17631.2,
    "ma200": 16751.4
  },
  "btc": {
    "price": 76265.0,
    "chgAbs": -1274.1719,
    "chgPct": -1.6433,
    "ma50": 76398.39,
    "ma200": 80788.81
  },
  "vix": {
    "price": 16.65,
    "chgAbs": -0.11,
    "chgPct": -0.6563,
    "ma50": 20.78,
    "ma200": 18.36
  },
  "gold": {
    "price": 4509.5,
    "chgAbs": -30.2998,
    "chgPct": -0.6674,
    "ma50": 4668.63,
    "ma200": 4348.46
  },
  "oil": {
    "price": 96.72,
    "chgAbs": 0.37,
    "chgPct": 0.384,
    "ma50": 98.38,
    "ma200": 71.52
  },
  "eurusd": {
    "price": 1.1613,
    "chgAbs": -0.0012,
    "chgPct": -0.1061,
    "ma50": 1.17,
    "ma200": 1.17
  },
  "dxy": {
    "price": 99.26,
    "chgAbs": 0.07,
    "chgPct": 0.0706,
    "ma50": 98.97,
    "ma200": 98.55
  },
  "ust10": {
    "price": 4.558,
    "chgAbs": -0.028,
    "chgPct": -0.6106,
    "ma50": 4.37,
    "ma200": 4.2
  },
  "ust2": {
    "price": 3.585,
    "chgAbs": 0.003,
    "chgPct": 0.0838,
    "ma50": 3.6,
    "ma200": 3.71
  },
  "_meta": {
    "updated_utc": "2026-05-22T19:26:58.300066+00:00",
    "ok": 11,
    "total": 11,
    "source": "Yahoo Finance (free, no API key)"
  }
}