{
  "spx": {
    "price": 7254.46,
    "chgAbs": 45.4502,
    "chgPct": 0.6305,
    "ma50": 6822.4,
    "ma200": 6728.57
  },
  "ndx": {
    "price": 27764.982,
    "chgAbs": 312.8629,
    "chgPct": 1.1397,
    "ma50": 25180.12,
    "ma200": 24824.03
  },
  "ibex": {
    "price": 17781.0,
    "chgAbs": 138.1992,
    "chgPct": 0.7833,
    "ma50": 17637.01,
    "ma200": 16486.84
  },
  "btc": {
    "price": 78522.19,
    "chgAbs": 2217.8697,
    "chgPct": 2.9066,
    "ma50": 72355.8,
    "ma200": 84021.18
  },
  "vix": {
    "price": 16.8,
    "chgAbs": -0.09,
    "chgPct": -0.5329,
    "ma50": 22.24,
    "ma200": 18.28
  },
  "gold": {
    "price": 4640.0,
    "chgAbs": 25.2998,
    "chgPct": 0.5482,
    "ma50": 4833.36,
    "ma200": 4254.48
  },
  "oil": {
    "price": 101.94,
    "chgAbs": -3.13,
    "chgPct": -2.979,
    "ma50": 91.18,
    "ma200": 68.99
  },
  "eurusd": {
    "price": 1.1737,
    "chgAbs": 0.0052,
    "chgPct": 0.4476,
    "ma50": 1.16,
    "ma200": 1.17
  },
  "dxy": {
    "price": 98.137,
    "chgAbs": 0.057,
    "chgPct": 0.0581,
    "ma50": 98.93,
    "ma200": 98.54
  },
  "ust10": {
    "price": 4.378,
    "chgAbs": -0.012,
    "chgPct": -0.2733,
    "ma50": 4.25,
    "ma200": 4.18
  },
  "ust2": {
    "price": 3.575,
    "chgAbs": -0.01,
    "chgPct": -0.2789,
    "ma50": 3.6,
    "ma200": 3.75
  },
  "_meta": {
    "updated_utc": "2026-05-01T17:54:32.823839+00:00",
    "ok": 11,
    "total": 11,
    "source": "Yahoo Finance (free, no API key)"
  }
}