{
  "spx": {
    "price": 7383.74,
    "chgAbs": -200.5701,
    "chgPct": -2.6445,
    "ma50": 7155.96,
    "ma200": 6858.26
  },
  "ndx": {
    "price": 28957.6,
    "chgAbs": -1450.2105,
    "chgPct": -4.7692,
    "ma50": 27446.08,
    "ma200": 25552.25
  },
  "ibex": {
    "price": 18344.9,
    "chgAbs": 68.9,
    "chgPct": 0.377,
    "ma50": 17878.17,
    "ma200": 16910.2
  },
  "btc": {
    "price": 61639.24,
    "chgAbs": -2162.3342,
    "chgPct": -3.3892,
    "ma50": 76393.29,
    "ma200": 78780.41
  },
  "vix": {
    "price": 21.51,
    "chgAbs": 6.11,
    "chgPct": 39.6753,
    "ma50": 18.99,
    "ma200": 18.42
  },
  "gold": {
    "price": 4353.9,
    "chgAbs": -121.8998,
    "chgPct": -2.7235,
    "ma50": 4624.4,
    "ma200": 4398.63
  },
  "oil": {
    "price": 90.25,
    "chgAbs": -2.79,
    "chgPct": -2.9987,
    "ma50": 97.86,
    "ma200": 72.79
  },
  "eurusd": {
    "price": 1.1527,
    "chgAbs": -0.0086,
    "chgPct": -0.7375,
    "ma50": 1.17,
    "ma200": 1.17
  },
  "dxy": {
    "price": 100.071,
    "chgAbs": 0.661,
    "chgPct": 0.6649,
    "ma50": 98.91,
    "ma200": 98.6
  },
  "ust10": {
    "price": 4.536,
    "chgAbs": 0.059,
    "chgPct": 1.3178,
    "ma50": 4.4,
    "ma200": 4.2
  },
  "ust2": {
    "price": 3.625,
    "chgAbs": 0.005,
    "chgPct": 0.1381,
    "ma50": 3.6,
    "ma200": 3.68
  },
  "_meta": {
    "updated_utc": "2026-06-05T21:54:29.620222+00:00",
    "ok": 11,
    "total": 11,
    "source": "Yahoo Finance (free, no API key)"
  }
}