{
  "spx": {
    "price": 6781.48,
    "chgAbs": -14.5102,
    "chgPct": -0.2135,
    "ma50": 6897.16,
    "ma200": 6591.49
  },
  "ndx": {
    "price": 24956.47,
    "chgAbs": -10.78,
    "chgPct": -0.0432,
    "ma50": 25262.06,
    "ma200": 24232.29
  },
  "ibex": {
    "price": 17387.1,
    "chgAbs": -57.9,
    "chgPct": -0.3319,
    "ma50": 17762.87,
    "ma200": 15886.28
  },
  "btc": {
    "price": 69471.66,
    "chgAbs": -455.2619,
    "chgPct": -0.6511,
    "ma50": 72809.42,
    "ma200": 94741.41
  },
  "vix": {
    "price": 25.29,
    "chgAbs": 0.36,
    "chgPct": 1.444,
    "ma50": 18.5,
    "ma200": 17.51
  },
  "gold": {
    "price": 5197.2,
    "chgAbs": -32.5002,
    "chgPct": -0.6215,
    "ma50": 4881.99,
    "ma200": 4008.69
  },
  "oil": {
    "price": 85.98,
    "chgAbs": 2.53,
    "chgPct": 3.0318,
    "ma50": 65.22,
    "ma200": 63.44
  },
  "eurusd": {
    "price": 1.1605,
    "chgAbs": -0.0012,
    "chgPct": -0.1053,
    "ma50": 1.18,
    "ma200": 1.17
  },
  "dxy": {
    "price": 98.966,
    "chgAbs": 0.136,
    "chgPct": 0.1376,
    "ma50": 98.04,
    "ma200": 98.38
  },
  "ust10": {
    "price": 4.136,
    "chgAbs": -0.0,
    "chgPct": -0.0,
    "ma50": 4.15,
    "ma200": 4.2
  },
  "ust2": {
    "price": 3.595,
    "chgAbs": 0.002,
    "chgPct": 0.0557,
    "ma50": 3.57,
    "ma200": 3.87
  },
  "_meta": {
    "updated_utc": "2026-03-11T11:52:27.817492+00:00",
    "ok": 11,
    "total": 11,
    "source": "Yahoo Finance (free, no API key)"
  }
}