{
  "spx": {
    "price": 7523.05,
    "chgAbs": 3.9299,
    "chgPct": 0.0523,
    "ma50": 7022.17,
    "ma200": 6819.22
  },
  "ndx": {
    "price": 29901.207,
    "chgAbs": -100.1133,
    "chgPct": -0.3337,
    "ma50": 26607.53,
    "ma200": 25322.84
  },
  "ibex": {
    "price": 18394.7,
    "chgAbs": 103.7996,
    "chgPct": 0.5675,
    "ma50": 17701.63,
    "ma200": 16804.07
  },
  "btc": {
    "price": 74763.97,
    "chgAbs": -1061.7644,
    "chgPct": -1.4003,
    "ma50": 77133.26,
    "ma200": 80130.35
  },
  "vix": {
    "price": 16.88,
    "chgAbs": -0.13,
    "chgPct": -0.7643,
    "ma50": 20.33,
    "ma200": 18.37
  },
  "gold": {
    "price": 4483.7,
    "chgAbs": -16.6999,
    "chgPct": -0.3711,
    "ma50": 4647.62,
    "ma200": 4359.24
  },
  "oil": {
    "price": 89.78,
    "chgAbs": -4.11,
    "chgPct": -4.3775,
    "ma50": 98.21,
    "ma200": 71.8
  },
  "eurusd": {
    "price": 1.1652,
    "chgAbs": 0.0015,
    "chgPct": 0.1256,
    "ma50": 1.17,
    "ma200": 1.17
  },
  "dxy": {
    "price": 99.063,
    "chgAbs": -0.087,
    "chgPct": -0.0877,
    "ma50": 98.93,
    "ma200": 98.56
  },
  "ust10": {
    "price": 4.467,
    "chgAbs": -0.026,
    "chgPct": -0.5787,
    "ma50": 4.38,
    "ma200": 4.2
  },
  "ust2": {
    "price": 3.585,
    "chgAbs": 0.003,
    "chgPct": 0.0838,
    "ma50": 3.6,
    "ma200": 3.7
  },
  "_meta": {
    "updated_utc": "2026-05-27T14:23:24.959355+00:00",
    "ok": 11,
    "total": 11,
    "source": "Yahoo Finance (free, no API key)"
  }
}